mlshell/__init__.py
mlshell/__version__.py
mlshell/conf.py
mlshell/blocks/__init__.py
mlshell/blocks/decomposition.py
mlshell/blocks/decorator.py
mlshell/blocks/plot.py
mlshell/blocks/preprocessing.py
mlshell/blocks/model_selection/__init__.py
mlshell/blocks/model_selection/prediction.py
mlshell/blocks/model_selection/resolve.py
mlshell/blocks/model_selection/search.py
mlshell/blocks/model_selection/validation.py
mlshell/blocks/pipeline/__init__.py
mlshell/blocks/pipeline/steps.py
mlshell/producers/__init__.py
mlshell/producers/dataset.py
mlshell/producers/logger.py
mlshell/producers/metric.py
mlshell/producers/pipeline.py
mlshell/producers/workflow.py
mlshell-0.0.2.dist-info/METADATA
mlshell-0.0.2.dist-info/WHEEL
mlshell-0.0.2.dist-info/top_level.txt
mlshell-0.0.2.dist-info/RECORD
