Metadata-Version: 2.1
Name: mlshell
Version: 0.0.2
Summary: Ml framework.
Home-page: https://github.com/nizaevka/mlshell
Author: nizaevka
Author-email: knizaev@gmail.com
License: UNKNOWN
Project-URL: Documentation, https://mlshell.readthedocs.io/
Project-URL: Source, https://github.com/nizaevka/mlshell
Project-URL: Tracker, https://github.com/nizaevka/mlshell/issues
Keywords: ml sklearn workflow
Platform: UNKNOWN
Classifier: Development Status :: 3 - Alpha
Classifier: Programming Language :: Python :: 3
Classifier: License :: OSI Approved :: Apache Software License
Classifier: Operating System :: OS Independent
Requires-Python: >=3.6
Requires-Dist: pycnfg (==0.0.2)
Requires-Dist: jsbeautifier
Requires-Dist: scikit-learn (==0.23.2)
Requires-Dist: pandas
Requires-Dist: tabulate
Requires-Dist: matplotlib
Provides-Extra: dev
Requires-Dist: pytest ; extra == 'dev'
Requires-Dist: sphinx ; extra == 'dev'
Requires-Dist: sphinxcontrib-napoleon ; extra == 'dev'
Requires-Dist: sphinx-autodoc-typehints ; extra == 'dev'
Requires-Dist: sphinx-rtd-theme ; extra == 'dev'
Requires-Dist: numpydoc ; extra == 'dev'
Requires-Dist: line-profiler ; extra == 'dev'
Requires-Dist: memory-profiler ; extra == 'dev'
Requires-Dist: lightgbm ; extra == 'dev'
